{
	"class" : {
		 },
	"instance" : {
		"amplitudeAlpha:" : "AliakseiSyrel 8/19/2016 22:36",
		"amplitudeBlue:" : "AliakseiSyrel 8/19/2016 22:36",
		"amplitudeGreen:" : "AliakseiSyrel 8/19/2016 22:36",
		"amplitudeRed:" : "AliakseiSyrel 8/19/2016 22:36",
		"exponentAlpha:" : "AliakseiSyrel 8/19/2016 22:36",
		"exponentBlue:" : "AliakseiSyrel 8/19/2016 22:36",
		"exponentGreen:" : "AliakseiSyrel 8/19/2016 22:36",
		"exponentRed:" : "AliakseiSyrel 8/19/2016 22:36",
		"offsetAlpha:" : "AliakseiSyrel 8/19/2016 22:37",
		"offsetBlue:" : "AliakseiSyrel 8/19/2016 22:36",
		"offsetGreen:" : "AliakseiSyrel 8/19/2016 22:37",
		"offsetRed:" : "AliakseiSyrel 8/19/2016 22:36" } }
