{
	"class" : {
		"ffiLibraryName" : "AliakseiSyrel 10/2/2016 21:40:10" },
	"instance" : {
		"fillPath:withLinearGradient:" : "AliakseiSyrel 10/2/2016 21:40:10",
		"fillPath:withPattern:" : "AliakseiSyrel 10/2/2016 21:40:10",
		"fillPath:withRadialGradient:" : "AliakseiSyrel 10/2/2016 21:40:10",
		"fillPath:withSolidColor:" : "AliakseiSyrel 10/2/2016 21:40:10",
		"fillPath:withSurface:" : "AliakseiSyrel 10/2/2016 21:40:10",
		"fillRectangle:withLinearGradient:" : "AliakseiSyrel 10/2/2016 21:40:10",
		"fillRectangle:withPattern:" : "AliakseiSyrel 10/2/2016 21:40:10",
		"fillRectangle:withRadialGradient:" : "AliakseiSyrel 10/2/2016 21:40:10",
		"fillRectangle:withSolidColor:" : "AliakseiSyrel 10/2/2016 21:40:10",
		"fillRectangle:withSurface:" : "AliakseiSyrel 10/2/2016 21:40:10",
		"primFillPath:pattern:drawOptions:" : "AliakseiSyrel 10/2/2016 21:40:10",
		"primFillPathColor:r:g:b:a:drawOptions:" : "AliakseiSyrel 10/2/2016 21:40:10",
		"primFillRect:pattern:drawOptions:" : "AliakseiSyrel 10/2/2016 21:40:10",
		"primFillX:y:width:height:r:g:b:a:drawOptions:" : "AliakseiSyrel 10/2/2016 21:40:10" } }
